niftyterminal/__init__.py
niftyterminal/exceptions.py
niftyterminal/api/__init__.py
niftyterminal/api/commodity.py
niftyterminal/api/etf.py
niftyterminal/api/indices.py
niftyterminal/api/market.py
niftyterminal/api/stocks.py
niftyterminal/api/vix.py
niftyterminal/core/__init__.py
niftyterminal/core/session.py
niftyterminal/sample-output/get_all_etfs.json
niftyterminal/sample-output/get_all_index_quote.json
niftyterminal/sample-output/get_etf_historical_data.json
niftyterminal/sample-output/get_index_historical_data.json
niftyterminal/sample-output/get_index_list.json
niftyterminal/sample-output/get_index_stocks.json
niftyterminal/sample-output/get_stock_quote.json
niftyterminal/sample-output/get_stocks_list.json
niftyterminal/sample-output/get_vix_historical_data.json
niftyterminal-0.3.0.dist-info/METADATA
niftyterminal-0.3.0.dist-info/WHEEL
niftyterminal-0.3.0.dist-info/licenses/LICENSE
niftyterminal-0.3.0.dist-info/RECORD
