Metadata-Version: 2.4
Name: niftyterminal
Version: 0.3.0
Summary: A clean Python library for fetching Indian stock market data from NSE India
Project-URL: Homepage, https://github.com/Mwsurjith/niftyterminal
Project-URL: Repository, https://github.com/Mwsurjith/niftyterminal
Author-email: Surjith <mwsurjith51@gmail.com>
License-Expression: MIT
License-File: LICENSE
Keywords: finance,india,market,nifty,nse,stock,trading
Classifier: Development Status :: 3 - Alpha
Classifier: Intended Audience :: Developers
Classifier: License :: OSI Approved :: MIT License
Classifier: Programming Language :: Python :: 3
Classifier: Programming Language :: Python :: 3.9
Classifier: Programming Language :: Python :: 3.10
Classifier: Programming Language :: Python :: 3.11
Classifier: Programming Language :: Python :: 3.12
Classifier: Topic :: Office/Business :: Financial :: Investment
Requires-Python: >=3.9
Requires-Dist: httpx>=0.27.0
Requires-Dist: requests>=2.28.0
Provides-Extra: dev
Requires-Dist: pytest-cov>=4.0.0; extra == 'dev'
Requires-Dist: pytest>=7.0.0; extra == 'dev'
